mkdocs_simple_blog/__init__.py
mkdocs_simple_blog/assets/css/bootstrap.min.css
mkdocs_simple_blog/assets/css/bootstrap.min.css.map
mkdocs_simple_blog/assets/css/grayscale-dark.min.css
mkdocs_simple_blog/assets/css/main.min.css
mkdocs_simple_blog/assets/css/media.min.css
mkdocs_simple_blog/assets/css/mkdocstrings.min.css
mkdocs_simple_blog/assets/css/root.min.css
mkdocs_simple_blog/assets/img/favicon.ico
mkdocs_simple_blog/assets/img/logo.png
mkdocs_simple_blog/assets/js/bootstrap.bundle.min.js
mkdocs_simple_blog/assets/js/bootstrap.bundle.min.js.map
mkdocs_simple_blog/assets/js/jquery-3.3.1.slim.min.js
mkdocs_simple_blog/assets/js/main.min.js
mkdocs_simple_blog/base.html
mkdocs_simple_blog/main.html
mkdocs_simple_blog/mkdocs_theme.yml
mkdocs_simple_blog/modules/content.html
mkdocs_simple_blog/modules/copyright.html
mkdocs_simple_blog/modules/dropdown-menu.html
mkdocs_simple_blog/modules/footer.html
mkdocs_simple_blog/modules/head_extra_links.html
mkdocs_simple_blog/modules/header.html
mkdocs_simple_blog/modules/menu.html
mkdocs_simple_blog/modules/preview.html
mkdocs_simple_blog/modules/search.html
mkdocs_simple_blog/modules/searchbox.html
mkdocs_simple_blog/modules/sidebar.html
mkdocs_simple_blog/modules/source.html
mkdocs_simple_blog/search.html
mkdocs_simple_blog-0.3.0.dist-info/METADATA
mkdocs_simple_blog-0.3.0.dist-info/WHEEL
mkdocs_simple_blog-0.3.0.dist-info/entry_points.txt
mkdocs_simple_blog-0.3.0.dist-info/licenses/LICENSE
mkdocs_simple_blog-0.3.0.dist-info/RECORD
