Metadata-Version: 2.4
Name: mkdocs-simple-blog
Version: 0.3.0
Summary: Mkdocs Blog Theme
License: MIT License
License-File: LICENSE
Keywords: mkdocs,blog,theme,documentation
Author: Fernando Celmer
Author-email: email@fernandocelmer.com
Maintainer: Fernando Celmer
Maintainer-email: email@fernandocelmer.com
Requires-Python: >=3.9
Classifier: Development Status :: 4 - Beta
Classifier: Operating System :: OS Independent
Classifier: Intended Audience :: Developers
Classifier: Natural Language :: English
Classifier: Programming Language :: Python :: 3.9
Classifier: Programming Language :: Python :: 3.10
Classifier: Programming Language :: Python :: 3.11
Classifier: Programming Language :: Python :: 3.12
Classifier: Programming Language :: Python :: 3.13
Classifier: Programming Language :: Python :: 3.14
Requires-Dist: mkdocs (>=1.6.1,<2.0.0)
Project-URL: Changelog, https://fernandocelmer.github.io/mkdocs-simple-blog/nav/development/release-notes/
Project-URL: Documentation, https://fernandocelmer.github.io/mkdocs-simple-blog
Project-URL: Homepage, https://github.com/FernandoCelmer/mkdocs-simple-blog
Project-URL: Issues, https://github.com/FernandoCelmer/mkdocs-simple-blog/issues
Project-URL: Repository, https://github.com/FernandoCelmer/mkdocs-simple-blog
